fb_python_sdk-1.1.7.dist-info/licenses/LICENSE
fbclient/__init__.py
fbclient/category.py
fbclient/client.py
fbclient/common_types.py
fbclient/config.py
fbclient/data_storage.py
fbclient/evaluator.py
fbclient/event_processor.py
fbclient/event_types.py
fbclient/flag_change_notification.py
fbclient/interfaces.py
fbclient/notice_broadcaster.py
fbclient/status.py
fbclient/status_types.py
fbclient/streaming.py
fbclient/update_processor.py
fbclient/utils/__init__.py
fbclient/utils/exponential_backoff_jitter_strategy.py
fbclient/utils/http_client.py
fbclient/utils/repeatable_task.py
fbclient/utils/rwlock.py
fbclient/utils/variation_splitting_algorithm.py
tests/__init__.py
tests/test_data_storage.py
tests/test_data_update_status_provider.py
tests/test_evaluator.py
tests/test_event_processor.py
tests/test_fbclient.py
tests/test_flag_change_notification.py
fb_python_sdk-1.1.7.dist-info/METADATA
fb_python_sdk-1.1.7.dist-info/WHEEL
fb_python_sdk-1.1.7.dist-info/top_level.txt
fb_python_sdk-1.1.7.dist-info/RECORD
