Metadata-Version: 2.4
Name: fb-python-sdk
Version: 1.1.7
Summary: A Python SDK for FeatBit plateform
Home-page: https://github.com/featbit/featbit-python-sdk
Author: Dian SUN
Author-email: featbit.master@gmail.com
Project-URL: Code, https://github.com/featbit/featbit-python-sdk
Project-URL: Issue tracker, https://github.com/featbit/featbit/issues
Classifier: Development Status :: 5 - Production/Stable
Classifier: Intended Audience :: Developers
Classifier: License :: OSI Approved :: Apache Software License
Classifier: Operating System :: OS Independent
Classifier: Topic :: Software Development
Classifier: Topic :: Software Development :: Libraries
Classifier: Programming Language :: Python :: 3.6
Classifier: Programming Language :: Python :: 3.7
Classifier: Programming Language :: Python :: 3.8
Classifier: Programming Language :: Python :: 3.9
Classifier: Programming Language :: Python :: 3.10
Classifier: Programming Language :: Python :: 3.11
Classifier: Programming Language :: Python :: 3.12
Requires-Python: >=3.6, <3.13
License-File: LICENSE
Requires-Dist: certifi>=2018.4.16
Requires-Dist: urllib3>=1.22.0
Requires-Dist: python-dateutil>=2.8.2
Requires-Dist: websocket-client>=1.0.0
Provides-Extra: dev
Requires-Dist: certifi>=2018.4.16; extra == "dev"
Requires-Dist: urllib3>=1.22.0; extra == "dev"
Requires-Dist: websocket-client>=1.0.0; extra == "dev"
Requires-Dist: python-dateutil>=2.8.2; extra == "dev"
Requires-Dist: flake8; extra == "dev"
Requires-Dist: pytest; extra == "dev"
Requires-Dist: pytest-mock; extra == "dev"
Requires-Dist: autopep8; extra == "dev"
Requires-Dist: build; extra == "dev"
Requires-Dist: twine; extra == "dev"
Dynamic: author
Dynamic: author-email
Dynamic: classifier
Dynamic: description
Dynamic: description-content-type
Dynamic: home-page
Dynamic: license-file
Dynamic: project-url
Dynamic: provides-extra
Dynamic: requires-dist
Dynamic: requires-python
Dynamic: summary
